tse_motion/__init__.py
tse_motion/inference_motion.py
tse_motion/model.py
tse_motion/motion2d.py
tse_motion/nii2mp4.py
tse_motion/rate.py
tse_motion/reconstruction.py
tse_motion/remove_background.py
tse_motion/translate_t1.py
tse_motion/unet-checkpoint.pth
tse_motion/unet.py
tse_motion/utils.py
tse_motion/weight.pth
tse_motion-0.2.8.6.dist-info/LICENSE
tse_motion-0.2.8.6.dist-info/METADATA
tse_motion-0.2.8.6.dist-info/WHEEL
tse_motion-0.2.8.6.dist-info/entry_points.txt
tse_motion-0.2.8.6.dist-info/top_level.txt
tse_motion-0.2.8.6.dist-info/RECORD
