Metadata-Version: 2.1
Name: tse_motion
Version: 0.2.8.6
Summary: A package to rate motion artifacts in medical images.
Home-page: https://github.com/jinghangli98/tse-rating
Author: Jinghang Li
Author-email: jinghang.li@pitt.edu
Classifier: Programming Language :: Python :: 3
Classifier: License :: OSI Approved :: MIT License
Classifier: Operating System :: OS Independent
License-File: LICENSE
Requires-Dist: torch
Requires-Dist: monai
Requires-Dist: nibabel
Requires-Dist: torchvision
Requires-Dist: argparse
